transport_docker_image.py
transport_docker_image-0.3.3.dist-info/METADATA
transport_docker_image-0.3.3.dist-info/WHEEL
transport_docker_image-0.3.3.dist-info/entry_points.txt
transport_docker_image-0.3.3.dist-info/RECORD
