Metadata-Version: 2.4
Name: transport-docker-image
Version: 0.3.3
Summary: transport docker image with best effort to reduce transmission size
Requires-Python: >=3.11
Requires-Dist: paramiko>=3.5.1
